rapidagents/__init__.py
rapidagents/agent.py
rapidagents/llm_wrapper.py
rapidagents/tool_registry.py
rapidagents/tools.py
rapidagents-0.1.0.dist-info/METADATA
rapidagents-0.1.0.dist-info/WHEEL
rapidagents-0.1.0.dist-info/RECORD
