Metadata-Version: 2.1
Name: rapidagents
Version: 0.1.0
Summary: A simple framework for building AI agents
License: MIT
Author: JHart96
Author-email: jordan.da.hart@gmail.com
Requires-Python: >=3.10,<4.0
Classifier: License :: OSI Approved :: MIT License
Classifier: Programming Language :: Python :: 3
Classifier: Programming Language :: Python :: 3.10
Classifier: Programming Language :: Python :: 3.11
Classifier: Programming Language :: Python :: 3.12
Requires-Dist: llm (>=0.15,<0.16)
